{
  "id": "9768d1a1-12a5-43ad-bd95-1a57a3dbfef5",
  "prevId": "359691c5-26ea-4233-b96f-f3c1f672fe38",
  "version": "7",
  "dialect": "postgresql",
  "tables": {
    "public.bills": {
      "name": "bills",
      "schema": "",
      "columns": {
        "id": {
          "name": "id",
          "type": "uuid",
          "primaryKey": true,
          "notNull": true,
          "default": "gen_random_uuid()"
        },
        "provider_id": {
          "name": "provider_id",
          "type": "uuid",
          "primaryKey": false,
          "notNull": true
        },
        "provider_name": {
          "name": "provider_name",
          "type": "text",
          "primaryKey": false,
          "notNull": true
        },
        "items": {
          "name": "items",
          "type": "jsonb",
          "primaryKey": false,
          "notNull": true
        },
        "total": {
          "name": "total",
          "type": "numeric(10, 2)",
          "primaryKey": false,
          "notNull": true
        },
        "date": {
          "name": "date",
          "type": "timestamp",
          "primaryKey": false,
          "notNull": false,
          "default": "now()"
        },
        "signer": {
          "name": "signer",
          "type": "text",
          "primaryKey": false,
          "notNull": false
        },
        "created_at": {
          "name": "created_at",
          "type": "timestamp",
          "primaryKey": false,
          "notNull": false,
          "default": "now()"
        }
      },
      "indexes": {},
      "foreignKeys": {
        "bills_provider_id_providers_id_fk": {
          "name": "bills_provider_id_providers_id_fk",
          "tableFrom": "bills",
          "tableTo": "providers",
          "columnsFrom": [
            "provider_id"
          ],
          "columnsTo": [
            "id"
          ],
          "onDelete": "no action",
          "onUpdate": "no action"
        },
        "bills_signer_signers_name_fk": {
          "name": "bills_signer_signers_name_fk",
          "tableFrom": "bills",
          "tableTo": "signers",
          "columnsFrom": [
            "signer"
          ],
          "columnsTo": [
            "name"
          ],
          "onDelete": "no action",
          "onUpdate": "no action"
        }
      },
      "compositePrimaryKeys": {},
      "uniqueConstraints": {},
      "checkConstraints": {}
    },
    "public.providers": {
      "name": "providers",
      "schema": "",
      "columns": {
        "id": {
          "name": "id",
          "type": "uuid",
          "primaryKey": true,
          "notNull": true,
          "default": "gen_random_uuid()"
        },
        "name": {
          "name": "name",
          "type": "text",
          "primaryKey": false,
          "notNull": true
        },
        "mobile": {
          "name": "mobile",
          "type": "text",
          "primaryKey": false,
          "notNull": true
        },
        "address": {
          "name": "address",
          "type": "text",
          "primaryKey": false,
          "notNull": false
        }
      },
      "indexes": {},
      "foreignKeys": {},
      "compositePrimaryKeys": {},
      "uniqueConstraints": {},
      "checkConstraints": {}
    },
    "public.signers": {
      "name": "signers",
      "schema": "",
      "columns": {
        "id": {
          "name": "id",
          "type": "uuid",
          "primaryKey": true,
          "notNull": true,
          "default": "gen_random_uuid()"
        },
        "name": {
          "name": "name",
          "type": "text",
          "primaryKey": false,
          "notNull": true
        }
      },
      "indexes": {},
      "foreignKeys": {},
      "compositePrimaryKeys": {},
      "uniqueConstraints": {
        "signers_name_unique": {
          "name": "signers_name_unique",
          "nullsNotDistinct": false,
          "columns": [
            "name"
          ]
        }
      },
      "checkConstraints": {}
    },
    "public.vegetables": {
      "name": "vegetables",
      "schema": "",
      "columns": {
        "id": {
          "name": "id",
          "type": "uuid",
          "primaryKey": true,
          "notNull": true,
          "default": "gen_random_uuid()"
        },
        "name": {
          "name": "name",
          "type": "text",
          "primaryKey": false,
          "notNull": true
        },
        "is_available": {
          "name": "is_available",
          "type": "boolean",
          "primaryKey": false,
          "notNull": false,
          "default": true
        },
        "has_fixed_price": {
          "name": "has_fixed_price",
          "type": "boolean",
          "primaryKey": false,
          "notNull": false,
          "default": false
        },
        "fixed_price": {
          "name": "fixed_price",
          "type": "numeric(10, 2)",
          "primaryKey": false,
          "notNull": false
        }
      },
      "indexes": {},
      "foreignKeys": {},
      "compositePrimaryKeys": {},
      "uniqueConstraints": {},
      "checkConstraints": {}
    }
  },
  "enums": {},
  "schemas": {},
  "sequences": {},
  "views": {},
  "_meta": {
    "columns": {},
    "schemas": {},
    "tables": {}
  }
}